LICENSE
MANIFEST.in
README.rst
setup.py
dj_api_auth2.egg-info/PKG-INFO
dj_api_auth2.egg-info/SOURCES.txt
dj_api_auth2.egg-info/dependency_links.txt
dj_api_auth2.egg-info/top_level.txt
djapiauth/__init__.py
djapiauth/admin.py
djapiauth/apps.py
djapiauth/auth.py
djapiauth/forms.py
djapiauth/models.py
djapiauth/tests.py
djapiauth/utility.py
djapiauth/views.py
djapiauth/management/__init__.py
djapiauth/management/commands/__init__.py
djapiauth/management/commands/reloadentrypoints.py
djapiauth/management/commands/repairapikeys.py
djapiauth/migrations/0001_initial.py
djapiauth/migrations/0002_apikeys_apitree.py
djapiauth/migrations/0003_auto_20150801_1439.py
djapiauth/migrations/__init__.py
example/djapp/db.sqlite3
example/djapp/manage.py
example/djapp/requirements.txt
example/djapp/djapp/__init__.py
example/djapp/djapp/apis.py
example/djapp/djapp/apiurls.py
example/djapp/djapp/settings.py
example/djapp/djapp/urls.py
example/djapp/djapp/views.py
example/djapp/djapp/wsgi.py
example/test/test.js
example/test/test.py